plasen/__init__.py
plasen/fit_beta.py
plasen/phys_calc.py
plasen-0.1.7.7.dist-info/licenses/LICENSE
satlas/__init__.py
satlas/loglikelihood.py
satlas/profiles.py
satlas/style.py
satlas/version.py
satlas/example/example.py
satlas/models/__init__.py
satlas/models/basemodel.py
satlas/models/hfsmodel.py
satlas/models/linkedmodel.py
satlas/models/models.py
satlas/models/summodel.py
satlas/models/transformmodel.py
satlas/stats/__init__.py
satlas/stats/fitting.py
satlas/stats/emcee/__init__.py
satlas/stats/emcee/autocorr.py
satlas/stats/emcee/ensemble.py
satlas/stats/emcee/interruptible_pool.py
satlas/stats/emcee/mh.py
satlas/stats/emcee/mpi_pool.py
satlas/stats/emcee/ptsampler.py
satlas/stats/emcee/sampler.py
satlas/stats/emcee/tests.py
satlas/stats/emcee/utils.py
satlas/tqdm/__init__.py
satlas/tqdm/_tqdm.py
satlas/tqdm/_tqdm_gui.py
satlas/tqdm/_tqdm_pandas.py
satlas/tqdm/_utils.py
satlas/tqdm/_version.py
satlas/utilities/__init__.py
satlas/utilities/plotting.py
satlas/utilities/utilities.py
plasen-0.1.7.7.dist-info/METADATA
plasen-0.1.7.7.dist-info/WHEEL
plasen-0.1.7.7.dist-info/top_level.txt
plasen-0.1.7.7.dist-info/RECORD
