Metadata-Version: 2.4
Name: plasen
Version: 0.1.7.7
Summary: Processing toolbox for LAser Spectroscopy of Exotic Nuclei.
Author-email: Zhou Yan <yanzh@pku.edu.cn>
License: MIT License
Project-URL: Homepage, https://github.com/amaneitsu/plasen
Classifier: Programming Language :: Python :: 3
Classifier: Operating System :: OS Independent
Requires-Python: >=3.7
License-File: LICENSE
Requires-Dist: pandas
Requires-Dist: matplotlib
Requires-Dist: numpy
Requires-Dist: satlas2
Requires-Dist: findiff
Requires-Dist: brokenaxes
Dynamic: license-file
